radix_heap-0.1.0.dist-info/METADATA
radix_heap-0.1.0.dist-info/WHEEL
radix_heap-0.1.0.dist-info/license_files/LICENSE
radix_heap/__init__.py
radix_heap/__init__.pyi
radix_heap/py.typed
radix_heap/radix_heap.abi3.so
radix_heap-0.1.0.dist-info/RECORD
