Metadata-Version: 2.3
Name: radix-heap
Version: 0.1.0
Classifier: Programming Language :: Rust
Classifier: Programming Language :: Python :: Implementation :: CPython
Classifier: Programming Language :: Python :: Implementation :: PyPy
License-File: LICENSE
Summary: Monotone priority queue useful for shortest paths and more; wraps Rust's radix-heap crate
Author-email: RuneBlaze <runeblaze@protonmail.com>
Requires-Python: >=3.8
